[ 
    {
        "title": "第000期 一吻天荒", 
        "artist": "阿禹ayy", 
        "pic": "一吻天荒.jpg", 
        "mp3": "一吻天荒.mp3", 
        "lyric": "一吻天荒.lcr",
        "date": "2025年07月27号 阴", 
        "article": "<p>现在建的站，希望多留下点痕迹，这首歌感觉旋律可以啦，也有点孤独的感情出来</p><p>（这是原项目作者所留感觉不错留下了）谁在寻找大雨滂沱挣脱谁的怀抱</p><p>每分每秒对我都算是煎熬</p><p>谁对谁错爱多爱少不需要再计较</p><p>只是我就这样深爱过</p>"
    },
    {
        "title": "第001期 知我", 
        "artist": "国风堂", 
        "pic": "infinity-18861721.jpg", 
        "mp3": "知我1.mp3", 
        "lyric": "知我.srt",
        "date": "2025年07月27号 阴", 
        "article": "<p>嘿嘿，刚知道不久，感觉不错~~唱的有点深意，听起来挺舒服</p>"
    },
    {
        "title": "第002期 夜航星", 
        "artist": "蔡明希（不才）", 
        "pic": "夜航星.png", 
        "mp3": "夜航星.mp3", 
        "lyric": "夜航星.lcr",
        "date": "2025年07月28号 晴", 
        "article": "<p>这首歌我确实喜欢，我比较喜欢看三体，了解宇宙知识，看看宇宙的真理</p>"
    },
    {
        "title": "第003期 晴天", 
        "artist": "周杰伦", 
        "pic": "晴天.jpg", 
        "mp3": "晴天.mp3", 
        "lyric": "晴天.lcr",
        "date": "2025年07月28号 晴", 
        "article": "<p>现在建的站，希望多留下点痕迹,，这首应该都会吧，我们班目前可能是除了校歌国歌之类的最会唱了的，感觉唱的还不错，挺好的</p>"
    },
    {
        "title": "第004期 黑暗森林", 
        "artist": "（原曲：Schwarzer Regen）-雲翼星辰", 
        "pic": "黑暗森林.jpg", 
        "mp3": "黑暗森林.mp3", 
        "lyric": "黑暗森林.lcr",
        "date": "2025年07月28号 晴", 
        "article": "<p>又来了，喜欢看我的三体，三体是我目前看过最喜欢的小说了，很有深意，特别是章北海，现在还是暑假，初二也有时间折腾，哈哈，今天还好吧</p>"
    },
    {
        "title": "第005期 最伟大的作品(量子力学版)", 
        "artist": "原唱周杰伦，翻唱浮世叁千问", 
        "pic": "【最伟大的作品】量子力学版.jpg", 
        "mp3": "【最伟大的作品】量子力学版.mp3", 
        "lyric": "【最伟大的作品】量子力学版.srt",
        "date": "2025年07月28号20点 晴", 
        "article": "<p>一天N更的我，今天还去了碧桂园玩，又来琢磨量子力学了~~，就有点喜欢广义相对论之类的颠覆世界观的东西</p>"
    },
    {
        "title": "第006期 起风了(旧版)", 
        "artist": "买辣椒也用券", 
        "pic": "起风了.jpg", 
        "mp3": "起风了.mp3", 
        "lyric": "起风了.lcr",
        "date": "2025年07月29号16点 阴", 
        "article": "<p>准初三了，最后一个初中年纪了，又快到了分别了，想想那些同学，虽然只有三年但感觉还是比小学印象更深，更有趣味，虽然我们班成绩不好但是也有趣啊，不亏了</p><p>希望以后还会见面，留次纪念</p>"
    }

]
